metatime/__init__.py
metatime/annotator.py
metatime/config.py
metatime/dmec.py
metatime/loaddata.py
metatime/mecmapper.py
metatime/mecs.py
metatime/plmapper.py
metatime/pretrained/mec/MeC_allgene_average-weights.tsv
metatime/pretrained/mec/MeC_allgene_average-weights.txt
metatime/pretrained/mec/MeC_anno.tsv
metatime/pretrained/mec/MeC_anno.txt
metatime/pretrained/mec/MeC_anno_name.tsv
metatime/pretrained/mec/MeC_anno_name.txt
metatime/pretrained/mec/MeC_topgene.tsv
metatime/pretrained/mec/MeC_topgene.txt
metatime/pretrained/mec/comp_cluster_labels.tsv
metatime/pretrained/mec/comp_cluster_labels.txt
metatime-1.3.0.dist-info/LICENSE
metatime-1.3.0.dist-info/METADATA
metatime-1.3.0.dist-info/WHEEL
metatime-1.3.0.dist-info/top_level.txt
metatime-1.3.0.dist-info/RECORD
