Metadata-Version: 2.1
Name: metatime
Version: 1.3.0
Summary: Beta MetaTiME: annotate TME scRNA cell states
Home-page: https://github.com/yi-zhang/MetaTiME.git
Author: Yi Zhang
Author-email: wingsyiz@gmail.com
License: UNKNOWN
Platform: UNKNOWN
Classifier: Development Status :: 3 - Alpha
Classifier: Intended Audience :: Science/Research
Classifier: Topic :: Scientific/Engineering :: Bio-Informatics
Classifier: Natural Language :: English
Classifier: Programming Language :: Python :: 3
Classifier: License :: OSI Approved :: GNU General Public License v3 or later (GPLv3+)
Classifier: Operating System :: OS Independent
Requires-Python: >=3.6
Requires-Dist: pandas
Requires-Dist: scanpy
Requires-Dist: anndata
Requires-Dist: matplotlib
Requires-Dist: adjustText
Requires-Dist: leidenalg
Requires-Dist: harmonypy
Requires-Dist: scipy
Requires-Dist: seaborn
